flask_bcs.py
Flask_BCS-0.9.1.dist-info/DESCRIPTION.rst
Flask_BCS-0.9.1.dist-info/METADATA
Flask_BCS-0.9.1.dist-info/metadata.json
Flask_BCS-0.9.1.dist-info/RECORD
Flask_BCS-0.9.1.dist-info/top_level.txt
Flask_BCS-0.9.1.dist-info/WHEEL
pybcs/bcs.py
pybcs/bucket.py
pybcs/common.py
pybcs/httpc.py
pybcs/object.py
pybcs/__init__.py
