Metadata-Version: 2.0
Name: Flask-BCS
Version: 0.9.1
Summary: Baidu Cloud Storage for Flask
Home-page: https://github.com/csuzhangxc/Flask-BCS
Author: Zhang Xuecheng
Author-email: csuzhangxc@gmail.com
License: MIT
Keywords: bcs for flask
Platform: any
Classifier: Development Status :: 4 - Beta
Classifier: Environment :: Web Environment
Classifier: Intended Audience :: Developers
Classifier: License :: OSI Approved :: MIT License
Classifier: Operating System :: OS Independent
Classifier: Programming Language :: Python
Classifier: Topic :: Internet :: WWW/HTTP :: Dynamic Content
Classifier: Topic :: Software Development :: Libraries :: Python Modules
Requires-Dist: setuptools
Requires-Dist: Flask
